{"time": 1653756000, "ip": "185.72.203.254", "forecast": {"buienradar": {"temperature": null, "humidity": null, "wind_speed": null, "air_pressure": null, "rain": 0, "thunder": null, "time": 1653756000, "last_updated": null, "location": null, "sun_set": null, "sun_rise": null, "description": null}}, "ping_result": {"avg_rtt": 6.101, "max_rtt": 10.565, "min_rtt": 4.565, "loss": 0.0}, "weather": {"BuienRadar": {"temperature": 12.6, "humidity": 62.0, "wind_speed": 6.6, "air_pressure": 1019.6, "rain": 0, "thunder": 0, "time": 1653754800.0, "last_updated": 1653754800.0, "location": [52.5761865151627, 6.754423961898484], "sun_set": "2022-05-28T21:45:00", "sun_rise": "2022-05-28T05:24:00", "description": "Mix van opklaringen en middelbare of lage bewolking"}, "OpenWeatherMap": {"temperature": 13.47, "humidity": 63, "wind_speed": 6.89, "air_pressure": 1018, "rain": 0, "thunder": 0, "time": null, "last_updated": 1653755704, "location": null, "sun_set": 1653766853, "sun_rise": 1653707996, "description": "scattered clouds"}, "WeatherAPI": {"temperature": 14.1, "humidity": 50, "wind_speed": 28.1, "air_pressure": 1018.0, "rain": 0.0, "thunder": 0, "time": null, "last_updated": 1653755400, "location": null, "sun_set": null, "sun_rise": null, "description": "Partly cloudy"}, "WeatherBitIO": {"temperature": 13.3, "humidity": 59.2213, "wind_speed": 6.27362, "air_pressure": 1017.11, "rain": 0, "thunder": 0, "time": null, "last_updated": 1653754506, "location": "G0401", "sun_set": "19:42", "sun_rise": "03:17", "description": "Scattered clouds"}, "Meteomatics": {"temperature": 11.7, "humidity": null, "wind_speed": 5.2, "air_pressure": null, "rain": 0.0, "thunder": 0, "time": null, "last_updated": null, "location": null, "sun_set": "2022-05-28T19:39:00Z", "sun_rise": "2022-05-28T03:19:00Z", "description": 2}, "Aeris": {"temperature": 12.94, "humidity": 59, "wind_speed": 18.31, "air_pressure": 1021.1, "rain": 0, "thunder": 0, "time": null, "last_updated": 1653756000, "location": null, "sun_set": null, "sun_rise": null, "description": "Partly Cloudy"}, "Foreca": {"temperature": 13, "humidity": 50, "wind_speed": 6, "air_pressure": 1017.29, "rain": 0, "thunder": 1, "time": null, "last_updated": "2022-05-28T18:40+02:00", "location": null, "sun_set": null, "sun_rise": null, "description": "d400"}}}