{"time": 1653886200, "ip": "185.72.203.254", "forecast": {"buienradar": {"temperature": null, "humidity": null, "wind_speed": null, "air_pressure": null, "rain": 0, "thunder": null, "time": 1653886200, "last_updated": null, "location": null, "sun_set": null, "sun_rise": null, "description": null}}, "ping_result": {"avg_rtt": 5.102, "max_rtt": 6.233, "min_rtt": 4.265, "loss": 0.0}, "weather": {"BuienRadar": {"temperature": 4.9, "humidity": 97.0, "wind_speed": 0.7, "air_pressure": 1012.8, "rain": 0, "thunder": null, "time": 1653885000.0, "last_updated": 1653885000.0, "location": [52.5761865151627, 6.754423961898484], "sun_set": "2022-05-30T21:47:00", "sun_rise": "2022-05-30T05:22:00", "description": "Mix van opklaringen en middelbare of lage bewolking"}, "OpenWeatherMap": {"temperature": 6.97, "humidity": 73, "wind_speed": 1.41, "air_pressure": 1013, "rain": 0, "thunder": null, "time": null, "last_updated": 1653885904, "location": null, "sun_set": 1653939804, "sun_rise": 1653880677, "description": "overcast clouds"}, "WeatherAPI": {"temperature": 7.0, "humidity": 93, "wind_speed": 4.0, "air_pressure": 1012.0, "rain": 0.0, "thunder": null, "time": null, "last_updated": 1653885900, "location": null, "sun_set": null, "sun_rise": null, "description": "Partly cloudy"}, "WeatherBitIO": {"temperature": 7.7, "humidity": 90.5859, "wind_speed": 1.83941, "air_pressure": 1010.83, "rain": 0, "thunder": null, "time": null, "last_updated": 1653885305, "location": "G0401", "sun_set": "19:45", "sun_rise": "03:15", "description": "Broken clouds"}, "Meteomatics": {"temperature": 10.2, "humidity": null, "wind_speed": 2.2, "air_pressure": null, "rain": 0.0, "thunder": null, "time": null, "last_updated": null, "location": null, "sun_set": "2022-05-30T19:42:00Z", "sun_rise": "2022-05-30T03:17:00Z", "description": 4}, "Aeris": {"temperature": 6.22, "humidity": 92, "wind_speed": 2.78, "air_pressure": 1013.4, "rain": 0, "thunder": null, "time": null, "last_updated": 1653886200, "location": null, "sun_set": null, "sun_rise": null, "description": "Mostly Cloudy"}, "Foreca": {"temperature": 8, "humidity": 83, "wind_speed": 2, "air_pressure": 1012.67, "rain": 0, "thunder": 0, "time": null, "last_updated": "2022-05-30T06:50+02:00", "location": null, "sun_set": null, "sun_rise": null, "description": "d400"}}}