{"time": 1653120901, "ip": "185.72.203.254", "ping_result": {"avg_rtt": 5.341, "max_rtt": 5.996, "min_rtt": 4.757, "loss": 0.0}, "weather": {"WeatherBitIO": {"temperature": 14.5, "humidity": 75.3365, "wind_speed": 6.78269, "air_pressure": 1017.37, "rain": 0, "thunder": 0, "time": 0, "last_updated": 1653119405, "location": "G0401", "sun_set": "19:33", "sun_rise": "03:25", "description": "Scattered clouds"}, "WeatherAPI": {"temperature": 14.6, "humidity": 75, "wind_speed": 29.5, "air_pressure": 1019.0, "rain": 0, "thunder": 0, "time": 0, "last_updated": 1653120900, "location": 0, "sun_set": 0, "sun_rise": 0, "description": "Cloudy"}, "AccuWeather": null, "OpenWeatherMap": {"temperature": 15.61, "humidity": 81, "wind_speed": 7.85, "air_pressure": 1019, "rain": 0, "thunder": 0, "time": 0, "last_updated": 1653120905, "location": 0, "sun_set": 1653161470, "sun_rise": 1653103695, "description": "broken clouds"}, "BuienRadar": {"temperature": 15.3, "humidity": 75.0, "wind_speed": 7.2, "air_pressure": 1018.7, "rain": 0, "thunder": 0, "time": "2022-05-21T10:00:00", "last_updated": "2022-05-21T10:00:00", "location": [52.5761865151627, 6.754423961898484], "sun_set": "2022-05-21T21:35:00", "sun_rise": "2022-05-21T05:33:00", "description": "Mix van opklaringen en middelbare of lage bewolking"}}}