{"time": 1653950400, "ip": "185.72.203.254", "forecast": {"buienradar": {"temperature": null, "humidity": null, "wind_speed": null, "air_pressure": null, "rain": 0, "thunder": null, "time": 1653950400, "last_updated": null, "location": null, "sun_set": null, "sun_rise": null, "description": null}}, "ping_result": {"avg_rtt": 5.944, "max_rtt": 10.336, "min_rtt": 4.545, "loss": 0.0}, "weather": {"BuienRadar": {"temperature": 7.0, "humidity": 95.0, "wind_speed": 1.4, "air_pressure": 1015.2, "rain": 0, "thunder": 0, "time": 1653949200.0, "last_updated": 1653949200.0, "location": [52.5761865151627, 6.754423961898484], "sun_set": "2022-05-30T21:47:00", "sun_rise": "2022-05-30T05:22:00", "description": "Zwaar bewolkt"}, "OpenWeatherMap": {"temperature": 8.52, "humidity": 83, "wind_speed": 2.8, "air_pressure": 1015, "rain": 0, "thunder": 0, "time": null, "last_updated": 1653950404, "location": null, "sun_set": 1654026277, "sun_rise": 1653967021, "description": "overcast clouds"}, "WeatherAPI": {"temperature": 8.4, "humidity": 85, "wind_speed": 9.7, "air_pressure": 1015.0, "rain": 0.0, "thunder": 0, "time": null, "last_updated": 1653949800, "location": null, "sun_set": null, "sun_rise": null, "description": "Partly cloudy"}, "WeatherBitIO": {"temperature": 9.3, "humidity": 81.7828, "wind_speed": 1.75745, "air_pressure": 1013.07, "rain": 0, "thunder": 0, "time": null, "last_updated": 1653948906, "location": "G0401", "sun_set": "19:46", "sun_rise": "03:15", "description": "Broken clouds"}, "Aeris": {"temperature": 8.79, "humidity": 86, "wind_speed": 2.78, "air_pressure": 1017.1, "rain": 0, "thunder": 0, "time": null, "last_updated": 1653950400, "location": null, "sun_set": null, "sun_rise": null, "description": "Cloudy"}, "Foreca": {"temperature": 7, "humidity": 85, "wind_speed": 1, "air_pressure": 1015.45, "rain": 0, "thunder": 0, "time": null, "last_updated": "2022-05-31T00:40+02:00", "location": null, "sun_set": null, "sun_rise": null, "description": "n300"}}}