{"time": 1654632600, "ip": "185.72.203.254", "forecast": {"buienradar": {"temperature": null, "humidity": null, "wind_speed": null, "air_pressure": null, "rain": 0, "thunder": null, "time": 1654632600, "last_updated": null, "location": null, "sun_set": null, "sun_rise": null, "description": null}}, "ping_result": {"avg_rtt": 5.446, "max_rtt": 6.743, "min_rtt": 4.387, "loss": 0.0}, "iperf_result": {"bits_per_sec": 13888849.334377574, "retransmissions": 371}, "weather": {"BuienRadar": {"temperature": 12.9, "humidity": 89.0, "wind_speed": 1.7, "air_pressure": 1011.8, "rain": 0, "thunder": 0, "time": 1654631400.0, "last_updated": 1654631400.0, "location": [52.5761865151627, 6.754423961898484], "sun_set": "2022-06-07T21:56:00", "sun_rise": "2022-06-07T05:16:00", "description": "Vrijwel onbewolkt (zonnig/helder)"}, "OpenWeatherMap": {"temperature": 13.04, "humidity": 89, "wind_speed": 2.67, "air_pressure": 1011, "rain": 0, "thunder": 0, "time": null, "last_updated": 1654632604, "location": null, "sun_set": 1654631520, "sun_rise": 1654571515, "description": "broken clouds"}, "WeatherAPI": {"temperature": 12.5, "humidity": 88, "wind_speed": 8.3, "air_pressure": 1011.0, "rain": 0.0, "thunder": 0, "time": null, "last_updated": 1654628400, "location": null, "sun_set": null, "sun_rise": null, "description": "Sunny"}, "WeatherBitIO": {"temperature": 12.2, "humidity": 86, "wind_speed": 1.31465, "air_pressure": 1009.64, "rain": 0, "thunder": 0, "time": null, "last_updated": 1654630800, "location": "G0401", "sun_set": "19:53", "sun_rise": "03:09", "description": "Clear sky"}, "Aeris": {"temperature": 13.98, "humidity": 84, "wind_speed": 8.17, "air_pressure": 1013.1, "rain": 0, "thunder": 0, "time": null, "last_updated": 1654632600, "location": null, "sun_set": null, "sun_rise": null, "description": "Mostly Clear"}, "Foreca": {"temperature": 15, "humidity": 81, "wind_speed": 1, "air_pressure": 1011.54, "rain": 0, "thunder": 0, "time": null, "last_updated": "2022-06-07T22:10+02:00", "location": null, "sun_set": null, "sun_rise": null, "description": "n100"}}}