{"time": 1654933500, "ip": "185.72.203.254", "forecast": {"foreca": {"temperature": 20, "humidity": 64, "wind_speed": 5, "air_pressure": 1021.46, "rain": 0, "thunder": 0, "time": 1654933500, "last_updated": null, "location": null, "sun_set": null, "sun_rise": null, "description": "d100"}, "buienradar": {"temperature": null, "humidity": null, "wind_speed": null, "air_pressure": null, "rain": 0, "thunder": null, "time": 1654933500, "last_updated": null, "location": null, "sun_set": null, "sun_rise": null, "description": null}}, "ping_result": {"avg_rtt": 5.584, "max_rtt": 7.579, "min_rtt": 4.182, "loss": 0.0}, "iperf_result": {"bits_per_sec": 13401984.39581922, "retransmissions": 348}, "weather": {"BuienRadar": {"temperature": 17.2, "humidity": 78.0, "wind_speed": 5.5, "air_pressure": 1021.3, "rain": 0, "thunder": null, "time": 1654932000.0, "last_updated": 1654932000.0, "location": [52.5761865151627, 6.754423961898484], "sun_set": "2022-06-11T21:59:00", "sun_rise": "2022-06-11T05:15:00", "description": "Vrijwel onbewolkt (zonnig/helder)"}, "OpenWeatherMap": {"temperature": 18.02, "humidity": 80, "wind_speed": 5.2, "air_pressure": 1021, "rain": 0, "thunder": null, "time": null, "last_updated": 1654933203, "location": null, "sun_set": 1654977317, "sun_rise": 1654917007, "description": "scattered clouds"}, "WeatherAPI": {"temperature": 16.4, "humidity": 76, "wind_speed": 23.0, "air_pressure": 1021.0, "rain": 0.0, "thunder": null, "time": null, "last_updated": 1654933500, "location": null, "sun_set": null, "sun_rise": null, "description": "Sunny"}, "WeatherBitIO": {"temperature": 18.3, "humidity": 74, "wind_speed": 5.12564, "air_pressure": 1019.82, "rain": 0, "thunder": null, "time": null, "last_updated": 1654932540, "location": "G0401", "sun_set": "19:56", "sun_rise": "03:08", "description": "Few clouds"}, "Aeris": {"temperature": 17.56, "humidity": 76, "wind_speed": 15.15, "air_pressure": 1023.4, "rain": 0, "thunder": null, "time": null, "last_updated": 1654933500, "location": null, "sun_set": null, "sun_rise": null, "description": "Partly Cloudy"}, "Foreca": {"temperature": 20, "humidity": 64, "wind_speed": 5, "air_pressure": 1021.46, "rain": 0, "thunder": 0, "time": null, "last_updated": "2022-06-11T09:45+02:00", "location": null, "sun_set": null, "sun_rise": null, "description": "d100"}}}