{"time": 1654137000, "ip": "185.72.203.254", "forecast": {"foreca": {"temperature": 7, "humidity": 97, "wind_speed": 2, "air_pressure": 1019.37, "rain": 0, "thunder": 0, "time": 1654137000, "last_updated": null, "location": null, "sun_set": null, "sun_rise": null, "description": "n000"}, "buienradar": {"temperature": null, "humidity": null, "wind_speed": null, "air_pressure": null, "rain": 0, "thunder": null, "time": 1654137000, "last_updated": null, "location": null, "sun_set": null, "sun_rise": null, "description": null}}, "ping_result": {"avg_rtt": 5.633, "max_rtt": 7.084, "min_rtt": 4.753, "loss": 0.0}, "weather": {"BuienRadar": {"temperature": 5.6, "humidity": 99.0, "wind_speed": 2.0, "air_pressure": 1019.7, "rain": 0, "thunder": 0, "time": 1654135800.0, "last_updated": 1654135800.0, "location": [52.5761865151627, 6.754423961898484], "sun_set": "2022-06-02T21:51:00", "sun_rise": "2022-06-02T05:20:00", "description": "Afwisselend bewolkt met lokaal mist(banken)"}, "OpenWeatherMap": {"temperature": 6.02, "humidity": 95, "wind_speed": 2.5, "air_pressure": 1020, "rain": 0, "thunder": 0, "time": null, "last_updated": 1654136404, "location": null, "sun_set": 1654199215, "sun_rise": 1654139719, "description": "clear sky"}, "WeatherAPI": {"temperature": 7.1, "humidity": 93, "wind_speed": 9.7, "air_pressure": 1020.0, "rain": 0.0, "thunder": 0, "time": null, "last_updated": 1654136100, "location": null, "sun_set": null, "sun_rise": null, "description": "Clear"}, "WeatherBitIO": {"temperature": 5, "humidity": 97, "wind_speed": 1.50182, "air_pressure": 1018.02, "rain": 0, "thunder": 0, "time": null, "last_updated": 1654135680, "location": "G0401", "sun_set": "19:48", "sun_rise": "03:13", "description": "Clear sky"}, "Aeris": {"temperature": 5.66, "humidity": 96, "wind_speed": 2.78, "air_pressure": 1021.4, "rain": 0, "thunder": 0, "time": null, "last_updated": 1654137000, "location": null, "sun_set": null, "sun_rise": null, "description": "Mostly Clear"}, "Foreca": {"temperature": 7, "humidity": 97, "wind_speed": 2, "air_pressure": 1019.37, "rain": 0, "thunder": 0, "time": null, "last_updated": "2022-06-02T04:30+02:00", "location": null, "sun_set": null, "sun_rise": null, "description": "n100"}}}