{"time": 1655512200, "ip": "185.72.203.254", "forecast": {"foreca": {"temperature": 17, "humidity": 56, "wind_speed": 4, "air_pressure": 1017.65, "rain": 0, "thunder": 0, "time": 1655512200, "last_updated": null, "location": null, "sun_set": null, "sun_rise": null, "description": "n000"}, "buienradar": {"temperature": null, "humidity": null, "wind_speed": null, "air_pressure": null, "rain": 0, "thunder": null, "time": 1655512200, "last_updated": null, "location": null, "sun_set": null, "sun_rise": null, "description": null}}, "ping_result": {"avg_rtt": 5.02, "max_rtt": 6.757, "min_rtt": 4.259, "loss": 0.0}, "iperf_result": {"bits_per_sec": 13628100.379296763, "retransmissions": 424}, "weather": {"BuienRadar": {"temperature": 18.0, "humidity": 74.0, "wind_speed": 3.2, "air_pressure": 1016.6, "rain": 0, "thunder": null, "time": 1655511000.0, "last_updated": 1655511000.0, "location": [52.5761865151627, 6.754423961898484], "sun_set": "2022-06-17T22:02:00", "sun_rise": "2022-06-17T05:13:00", "description": "Vrijwel onbewolkt (zonnig/helder)"}, "OpenWeatherMap": {"temperature": 18.08, "humidity": 76, "wind_speed": 4, "air_pressure": 1017, "rain": 0, "thunder": null, "time": null, "last_updated": 1655512205, "location": null, "sun_set": 1655582350, "sun_rise": 1655521740, "description": "clear sky"}, "WeatherAPI": {"temperature": 18.2, "humidity": 73, "wind_speed": 14.8, "air_pressure": 1018.0, "rain": 0.0, "thunder": null, "time": null, "last_updated": 1655511300, "location": null, "sun_set": null, "sun_rise": null, "description": "Clear"}, "Aeris": {"temperature": 18.38, "humidity": 69, "wind_speed": 6.48, "air_pressure": 1019.1, "rain": 0, "thunder": null, "time": null, "last_updated": 1655512200, "location": null, "sun_set": null, "sun_rise": null, "description": "Clear"}, "Foreca": {"temperature": 17, "humidity": 56, "wind_speed": 4, "air_pressure": 1017.65, "rain": 0, "thunder": 0, "time": null, "last_updated": "2022-06-18T02:30+02:00", "location": null, "sun_set": null, "sun_rise": null, "description": "n000"}}}