{"time": 1655057700, "ip": "185.72.203.254", "forecast": {"foreca": {"temperature": 19, "humidity": 55, "wind_speed": 4, "air_pressure": 1019.62, "rain": 0, "thunder": 0, "time": 1655057700, "last_updated": null, "location": null, "sun_set": null, "sun_rise": null, "description": "d100"}, "buienradar": {"temperature": null, "humidity": null, "wind_speed": null, "air_pressure": null, "rain": 0, "thunder": null, "time": 1655057700, "last_updated": null, "location": null, "sun_set": null, "sun_rise": null, "description": null}}, "ping_result": {"avg_rtt": 7.491, "max_rtt": 14.427, "min_rtt": 5.117, "loss": 0.0}, "iperf_result": {"bits_per_sec": 13297971.8901726, "retransmissions": 253}, "weather": {"BuienRadar": {"temperature": 17.2, "humidity": 65.0, "wind_speed": 4.4, "air_pressure": 1020.6, "rain": 0, "thunder": null, "time": 1655056800.0, "last_updated": 1655056800.0, "location": [52.5761865151627, 6.754423961898484], "sun_set": "2022-06-12T22:00:00", "sun_rise": "2022-06-12T05:14:00", "description": "Vrijwel onbewolkt (zonnig/helder)"}, "OpenWeatherMap": {"temperature": 18.34, "humidity": 63, "wind_speed": 5.12, "air_pressure": 1020, "rain": 0, "thunder": null, "time": null, "last_updated": 1655057704, "location": null, "sun_set": 1655063759, "sun_rise": 1655003387, "description": "broken clouds"}, "WeatherAPI": {"temperature": 17.6, "humidity": 67, "wind_speed": 18.7, "air_pressure": 1020.0, "rain": 0.0, "thunder": null, "time": null, "last_updated": 1655057700, "location": null, "sun_set": null, "sun_rise": null, "description": "Sunny"}, "WeatherBitIO": {"temperature": 17.8, "humidity": 57, "wind_speed": 4.49918, "air_pressure": 1018.81, "rain": 0, "thunder": null, "time": null, "last_updated": 1655056680, "location": "G0401", "sun_set": "19:57", "sun_rise": "03:07", "description": "Clear sky"}, "Aeris": {"temperature": 17.2, "humidity": 62, "wind_speed": 12.21, "air_pressure": 1022.1, "rain": 0, "thunder": null, "time": null, "last_updated": 1655057700, "location": null, "sun_set": null, "sun_rise": null, "description": "Partly Cloudy"}, "Foreca": {"temperature": 19, "humidity": 55, "wind_speed": 4, "air_pressure": 1019.62, "rain": 0, "thunder": 0, "time": null, "last_updated": "2022-06-12T20:15+02:00", "location": null, "sun_set": null, "sun_rise": null, "description": "d100"}}}