{"time": 1655828700, "ip": "185.72.203.254", "forecast": {"buienradar": {"temperature": null, "humidity": null, "wind_speed": null, "air_pressure": null, "rain": 0, "thunder": null, "time": 1655828700, "last_updated": null, "location": null, "sun_set": null, "sun_rise": null, "description": null}}, "ping_result": {"avg_rtt": 5.239, "max_rtt": 6.995, "min_rtt": 4.462, "loss": 0.0}, "iperf_result": {"bits_per_sec": 13541092.0672938, "retransmissions": 381}, "weather": {"BuienRadar": {"temperature": 20.9, "humidity": 45.0, "wind_speed": 1.6, "air_pressure": 1013.9, "rain": 0, "thunder": null, "time": 1655827200.0, "last_updated": 1655827200.0, "location": [52.5761865151627, 6.754423961898484], "sun_set": "2022-06-21T22:04:00", "sun_rise": "2022-06-21T05:14:00", "description": "Zwaar bewolkt"}, "OpenWeatherMap": {"temperature": 21.93, "humidity": 57, "wind_speed": 1.83, "air_pressure": 1014, "rain": 0, "thunder": null, "time": null, "last_updated": 1655828104, "location": null, "sun_set": 1655841604, "sun_rise": 1655780960, "description": "overcast clouds"}, "WeatherAPI": {"temperature": 21.0, "humidity": 48, "wind_speed": 7.2, "air_pressure": 1014.0, "rain": 0.0, "thunder": null, "time": null, "last_updated": 1655828100, "location": null, "sun_set": null, "sun_rise": null, "description": "Cloudy"}, "Aeris": {"temperature": 23.39, "humidity": 41, "wind_speed": 3.7, "air_pressure": 1015.1, "rain": 0, "thunder": null, "time": null, "last_updated": 1655828700, "location": null, "sun_set": null, "sun_rise": null, "description": "Cloudy"}, "Foreca": {"temperature": 22, "humidity": 42, "wind_speed": 1, "air_pressure": 1013.12, "rain": 0.01, "thunder": 0, "time": null, "last_updated": "2022-06-21T18:25+02:00", "location": null, "sun_set": null, "sun_rise": null, "description": "d300"}}}