{"time": 1656303600, "ip": "185.72.203.254", "forecast": {"buienradar": {"temperature": null, "humidity": null, "wind_speed": null, "air_pressure": null, "rain": 0.2053525026457146, "thunder": null, "time": 1656303600, "last_updated": null, "location": null, "sun_set": null, "sun_rise": null, "description": null}}, "ping_result": {"avg_rtt": 5.97, "max_rtt": 7.119, "min_rtt": 4.987, "loss": 0.0}, "iperf_result": {"bits_per_sec": 12254923.468923505, "retransmissions": 0}, "weather": {"BuienRadar": {"temperature": 15.5, "humidity": 96.0, "wind_speed": 3.8, "air_pressure": 1015.2, "rain": 0.1, "thunder": null, "time": 1656302400.0, "last_updated": 1656302400.0, "location": [52.5761865151627, 6.754423961898484], "sun_set": "2022-06-27T22:04:00", "sun_rise": "2022-06-27T05:16:00", "description": "Zwaar bewolkt en regen"}, "OpenWeatherMap": {"temperature": 15.74, "humidity": 95, "wind_speed": 1.98, "air_pressure": 1015, "rain": 0, "thunder": null, "time": null, "last_updated": 1656303304, "location": null, "sun_set": 1656360023, "sun_rise": 1656299485, "description": "overcast clouds"}, "WeatherAPI": {"temperature": 15.3, "humidity": 89, "wind_speed": 8.3, "air_pressure": 1015.0, "rain": 0.0, "thunder": null, "time": null, "last_updated": 1656303300, "location": null, "sun_set": null, "sun_rise": null, "description": "Overcast"}, "Foreca": {"temperature": 16, "humidity": 95, "wind_speed": 3, "air_pressure": 1014.03, "rain": 0.04, "thunder": 0, "time": null, "last_updated": "2022-06-27T06:20+02:00", "location": null, "sun_set": null, "sun_rise": null, "description": "d400"}}}