{"time": 1656700500, "ip": "185.72.203.254", "forecast": {"buienradar": {"temperature": null, "humidity": null, "wind_speed": null, "air_pressure": null, "rain": 0, "thunder": null, "time": 1656700500, "last_updated": null, "location": null, "sun_set": null, "sun_rise": null, "description": null}}, "ping_result": {"avg_rtt": 5.588, "max_rtt": 7.62, "min_rtt": 4.718, "loss": 0.0}, "iperf_result": {"bits_per_sec": 13402358.30198577, "retransmissions": 291}, "weather": {"OpenWeatherMap": {"temperature": 19.36, "humidity": 63, "wind_speed": 4.59, "air_pressure": 1018, "rain": 0, "thunder": 0, "time": null, "last_updated": 1656699904, "location": null, "sun_set": 1656705570, "sun_rise": 1656645229, "description": "broken clouds"}, "WeatherAPI": {"temperature": 18.9, "humidity": 59, "wind_speed": 14.8, "air_pressure": 1018.0, "rain": 0.0, "thunder": 0, "time": null, "last_updated": 1656700200, "location": null, "sun_set": null, "sun_rise": null, "description": "Partly cloudy"}}}