{"time": 1657668900, "ip": "185.72.203.254", "forecast": {"buienradar": {"temperature": null, "humidity": null, "wind_speed": null, "air_pressure": null, "rain": 0, "thunder": null, "time": 1657668900, "last_updated": null, "location": null, "sun_set": null, "sun_rise": null, "description": null}}, "ping_result": {"avg_rtt": 5.093, "max_rtt": 6.226, "min_rtt": 4.601, "loss": 0.0}, "iperf_result": {"bits_per_sec": 12944682.469732525, "retransmissions": 121}, "weather": {"BuienRadar": {"temperature": 18.0, "humidity": 92.0, "wind_speed": 1.1, "air_pressure": 1021.2, "rain": 0, "thunder": null, "time": 1657668000.0, "last_updated": 1657668000.0, "location": [52.5761865151627, 6.754423961898484], "sun_set": "2022-07-12T21:56:00", "sun_rise": "2022-07-12T05:28:00", "description": "Zwaar bewolkt"}, "OpenWeatherMap": {"temperature": 20.32, "humidity": 87, "wind_speed": 2.89, "air_pressure": 1022, "rain": 0, "thunder": null, "time": null, "last_updated": 1657668312, "location": null, "sun_set": 1657741907, "sun_rise": 1657682712, "description": "light rain"}, "WeatherAPI": {"temperature": 19.7, "humidity": 61, "wind_speed": 9.7, "air_pressure": 1022.0, "rain": 0.0, "thunder": null, "time": null, "last_updated": 1657668600, "location": null, "sun_set": null, "sun_rise": null, "description": "Partly cloudy"}}}