{"time": 1657419600, "ip": "185.72.203.254", "forecast": {"buienradar": {"temperature": null, "humidity": null, "wind_speed": null, "air_pressure": null, "rain": 0, "thunder": null, "time": 1657419600, "last_updated": null, "location": null, "sun_set": null, "sun_rise": null, "description": null}}, "ping_result": {"avg_rtt": 5.108, "max_rtt": 6.233, "min_rtt": 4.679, "loss": 0.0}, "iperf_result": {"bits_per_sec": 13314087.819853676, "retransmissions": 176}, "weather": {"BuienRadar": {"temperature": 12.1, "humidity": 86.0, "wind_speed": 3.8, "air_pressure": 1025.6, "rain": 0, "thunder": null, "time": 1657418400.0, "last_updated": 1657418400.0, "location": [52.5761865151627, 6.754423961898484], "sun_set": "2022-07-10T21:58:00", "sun_rise": "2022-07-10T05:26:00", "description": "Vrijwel onbewolkt (zonnig/helder)"}, "OpenWeatherMap": {"temperature": 12.37, "humidity": 88, "wind_speed": 3.54, "air_pressure": 1026, "rain": 0, "thunder": null, "time": null, "last_updated": 1657419604, "location": null, "sun_set": 1657482864, "sun_rise": 1657423310, "description": "few clouds"}, "WeatherAPI": {"temperature": 11.0, "humidity": 89, "wind_speed": 13.7, "air_pressure": 1025.0, "rain": 0.0, "thunder": null, "time": null, "last_updated": 1657419300, "location": null, "sun_set": null, "sun_rise": null, "description": "Overcast"}}}