{"time": 1657053000, "ip": "185.72.203.254", "forecast": {"buienradar": {"temperature": null, "humidity": null, "wind_speed": null, "air_pressure": null, "rain": 0, "thunder": null, "time": 1657053000, "last_updated": null, "location": null, "sun_set": null, "sun_rise": null, "description": null}}, "ping_result": {"avg_rtt": 6.037, "max_rtt": 7.88, "min_rtt": 3.83, "loss": 0.0}, "iperf_result": {"bits_per_sec": 11548959.2760181, "retransmissions": 41}, "weather": {"BuienRadar": {"temperature": 13.8, "humidity": 77.0, "wind_speed": 3.1, "air_pressure": 1023.8, "rain": 0, "thunder": null, "time": 1657051800.0, "last_updated": 1657051800.0, "location": [52.5761865151627, 6.754423961898484], "sun_set": "2022-07-05T22:01:00", "sun_rise": "2022-07-05T05:21:00", "description": "Mix van opklaringen en middelbare of lage bewolking"}, "OpenWeatherMap": {"temperature": 14.58, "humidity": 87, "wind_speed": 3.32, "air_pressure": 1024, "rain": 0, "thunder": null, "time": null, "last_updated": 1657053004, "location": null, "sun_set": 1657051065, "sun_rise": 1656991017, "description": "scattered clouds"}, "WeatherAPI": {"temperature": 12.5, "humidity": 80, "wind_speed": 13.3, "air_pressure": 1023.0, "rain": 0.0, "thunder": null, "time": null, "last_updated": 1657052100, "location": null, "sun_set": null, "sun_rise": null, "description": "Sunny"}}}